elegant_heap_queue/__init__.py
elegant_heap_queue/comparable.py
elegant_heap_queue/heap_queue.py
elegant_heap_queue-1.0.0.dist-info/LICENSE.txt
elegant_heap_queue-1.0.0.dist-info/METADATA
elegant_heap_queue-1.0.0.dist-info/WHEEL
elegant_heap_queue-1.0.0.dist-info/top_level.txt
elegant_heap_queue-1.0.0.dist-info/RECORD
