Metadata-Version: 2.1
Name: elegant-heap-queue
Version: 1.0.0
Home-page: https://github.com/AlexanderChiuy/ElegantHeapQueue
License-File: LICENSE.txt
